setup.py
monetSpider/__init__.py
monetSpider/__main__.py
monetSpider/items.py
monetSpider/loaders.py
monetSpider/middlewares.py
monetSpider/pipelines.py
monetSpider/settings.py
monetSpider/spiders/XspiderSpider.py
monetSpider/spiders/__init__.py
monetSpider/url/Preprocessor.py
monetSpider/url/__init__.py
monetSpider/utils/__init__.py
monetSpider/utils/xml.py
monetSpider/xspider/Xspider.py
monetSpider/xspider/__init__.py
zpspider.egg-info/PKG-INFO
zpspider.egg-info/SOURCES.txt
zpspider.egg-info/dependency_links.txt
zpspider.egg-info/entry_points.txt
zpspider.egg-info/not-zip-safe
zpspider.egg-info/requires.txt
zpspider.egg-info/top_level.txt